pgpydriver/__init__.py
pgpydriver/_querydata.py
pgpydriver/driver.py
pgpydriver/querydata.py
pgpydriver/querytype.py
pgpydriver/sqlbuilder.py
pgpydriver-0.0.1b3.dist-info/METADATA
pgpydriver-0.0.1b3.dist-info/WHEEL
pgpydriver-0.0.1b3.dist-info/top_level.txt
pgpydriver-0.0.1b3.dist-info/RECORD
