Metadata-Version: 2.1
Name: pgpydriver
Version: 0.0.1b3
Summary: postgresql接続ドライバー
Home-page: https://gitlab.com/Nozomi0720/pypg-driver.git
Author: nozomi.nishinohara
Author-email: nozomi.nishinohara@belldata.co.jp
License: UNKNOWN
Platform: UNKNOWN
Classifier: Programming Language :: Python :: 3.6
Classifier: Programming Language :: Python :: 3.7
Requires-Dist: psycopg2 (>=2.8.3)
Requires-Dist: asyncio (>=3.4.3)
Requires-Dist: tornado (>=6.0.3)
